[
  {
    "id": 1,
    "user_id": "@guest-a",
    "event_id": 1,
    "row_number": 3,
    "start_time": "2023-01-06T18:00:33.621Z",
    "end_time": "2023-01-06T18:30:33.621Z"
  },
  {
    "id": 2,
    "user_id": "@guest-b",
    "event_id": 2,
    "row_number": 3,
    "start_time": "2023-01-06T18:30:33.621Z",
    "end_time": "2023-01-06T19:00:33.621Z"
  },
  {
    "id": 3,
    "user_id": "@guest-c",
    "event_id": 3,
    "row_number": 3,
    "start_time": "2023-01-06T18:00:33.621Z",
    "end_time": "2023-01-06T18:30:33.621Z"
  }
]
